LICENSE
MANIFEST.in
README.md
pyproject.toml
setup.cfg
setup.py
tap_google_search_console/__init__.py
tap_google_search_console/client.py
tap_google_search_console/discover.py
tap_google_search_console/exceptions.py
tap_google_search_console/helpers.py
tap_google_search_console/sync.py
tap_google_search_console/transform.py
tap_google_search_console.egg-info/PKG-INFO
tap_google_search_console.egg-info/SOURCES.txt
tap_google_search_console.egg-info/dependency_links.txt
tap_google_search_console.egg-info/entry_points.txt
tap_google_search_console.egg-info/requires.txt
tap_google_search_console.egg-info/top_level.txt
tap_google_search_console/schemas/performance_report_country.json
tap_google_search_console/schemas/performance_report_custom.json
tap_google_search_console/schemas/performance_report_date.json
tap_google_search_console/schemas/performance_report_device.json
tap_google_search_console/schemas/performance_report_page.json
tap_google_search_console/schemas/performance_report_query.json
tap_google_search_console/schemas/sitemaps.json
tap_google_search_console/schemas/sites.json
tap_google_search_console/streams/__init__.py
tap_google_search_console/streams/abstract.py
tap_google_search_console/streams/performance_reports.py
tap_google_search_console/streams/sitemaps.py
tap_google_search_console/streams/sites.py