Metadata-Version: 2.1
Name: tap-google-search-console
Version: 1.1.0
Summary: Singer.io tap for extracting data from the Google Search Console API
Author: jeff.huth@bytecode.io
Classifier: Programming Language :: Python :: 3 :: Only
Provides-Extra: dev
License-File: LICENSE
